pymenu_cli/__init__.py
pymenu_cli/pymenu.py
pymenu_cli/models/__init__.py
pymenu_cli/models/menu.py
pymenu_cli/models/menu_item.py
pymenu_cli/ui/__init__.py
pymenu_cli/ui/styles.py
tests/__init__.py
tests/test_menu.py
tests/test_menu_item.py
tests/test_pymenu.py
pymenu_cli-1.0.7.dist-info/METADATA
pymenu_cli-1.0.7.dist-info/WHEEL
pymenu_cli-1.0.7.dist-info/entry_points.txt
pymenu_cli-1.0.7.dist-info/top_level.txt
pymenu_cli-1.0.7.dist-info/RECORD
