Metadata-Version: 2.1
Name: pymenu-cli
Version: 1.0.7
Summary: A Python library for creating interactive CLI menus
Home-page: https://github.com/moraneus/pymenu-cli
Author: Moraneus
Author-email: moraneus@gmail.com
License: MIT
Requires-Dist: colorama
Requires-Dist: art
